Workbook

Sheet Dashboard
A1: PayNow Integration Estimation
A2: Presale strategy for SCSKAP: low-budget-friendly phased approach with controlled scope and visible risk items.
A4: Recommended Strategy | J4: Option | K4: Min MD | L4: Max MD
A5: Start with Phase 0 fixed-scope discovery, then quote Phase 1 Lean MVP for Counter Sales only. Keep Field Power Integration as Phase 2. This protects margin because UOB API access, bank callback rules, SAP output technology, and SAP FI/AR clearing are not yet confirmed. | J5: Phase 0 | K5: 5 | L5: 8
J6: Lean P1 | K6: 45 | L6: 75
J7: Standard P1 | K7: 70 | L7: 110
J8: Phase 2 | K8: 30 | L8: 50
A10: Option | B10: Min MD | C10: Max MD | D10: Avg MD | E10: Positioning
A11: Phase 0 Discovery | B11: ='Phase Estimates'!C5 -> 5 | C11: ='Phase Estimates'!D5 -> 8 | D11: ='Phase Estimates'!E5 -> 6.5 | E11: Recommended first step
A12: Lean Phase 1 MVP | B12: ='Phase Estimates'!C6 -> 45 | C12: ='Phase Estimates'!D6 -> 75 | D12: ='Phase Estimates'!E6 -> 60 | E12: Best fit for low budget
A13: Standard Phase 1 | B13: ='Phase Estimates'!C7 -> 70 | C13: ='Phase Estimates'!D7 -> 110 | D13: ='Phase Estimates'!E7 -> 90 | E13: If customer wants reliability
A14: Phase 2 Field Power | B14: ='Phase Estimates'!C8 -> 30 | C14: ='Phase Estimates'!D8 -> 50 | D14: ='Phase Estimates'!E8 -> 40 | E14: Separate later phase
A16: Key Commercial Guardrails
A17: 1 | B17: Do not quote full scope until Phase 0 confirms UOB API, SAP output, and SAP update mechanism.
A18: 2 | B18: Use fixed price only for Phase 0 and tightly scoped Phase 1; exclude bank onboarding delays and major SAP redesign.
A19: 3 | B19: Base offer should be Lean Phase 1. Price exception handling, auto-clearing, dashboards, refunds, and Field Power separately.
A20: 4 | B20: Customer budget is low, but project should be framed as ERP payment integration, not only QR generation.

Sheet Phase Estimates
A1: Phase Estimates
A2: Summary options generated from the Work Breakdown sheet.
A4: Phase | B4: Scope | C4: Min MD | D4: Max MD | E4: Avg MD | F4: Best Use | G4: Commercial Model | H4: Elapsed Time | I4: Recommendation
A5: P0 | B5: Phase 0 Discovery and Design | C5: =SUMIF('Work Breakdown'!$A:$A,A5,'Work Breakdown'!$C:$C) -> 5 | D5: =SUMIF('Work Breakdown'!$A:$A,A5,'Work Breakdown'!$D:$D) -> 8 | E5: =(C5+D5)/2 -> 6.5 | F5: Recommended first | G5: Fixed price | H5: 1-2 weeks | I5: Fixed-scope technical discovery before build commitment
A6: P1L | B6: Lean Phase 1 MVP | C6: =SUMIF('Work Breakdown'!$A:$A,A6,'Work Breakdown'!$C:$C) -> 45 | D6: =SUMIF('Work Breakdown'!$A:$A,A6,'Work Breakdown'!$D:$D) -> 75 | E6: =(C6+D6)/2 -> 60 | F6: Best fit for low budget | G6: Fixed scope or capped T&M | H6: 6-8 weeks | I6: Counter Sales MVP with core QR/payment/callback/SAP confirmation
A7: P1S | B7: Standard Phase 1 | C7: =SUMIF('Work Breakdown'!$A:$A,A7,'Work Breakdown'!$C:$C) -> 70 | D7: =SUMIF('Work Breakdown'!$A:$A,A7,'Work Breakdown'!$D:$D) -> 110 | E7: =(C7+D7)/2 -> 90 | F7: Use if reliability matters more than lowest cost | G7: Scoped fixed price | H7: 8-12 weeks | I7: Lean MVP plus stronger validation, exception handling, and reconciliation
A8: P2 | B8: Phase 2 Field Power Integration | C8: =SUMIF('Work Breakdown'!$A:$A,A8,'Work Breakdown'!$C:$C) -> 30 | D8: =SUMIF('Work Breakdown'!$A:$A,A8,'Work Breakdown'!$D:$D) -> 50 | E8: =(C8+D8)/2 -> 40 | F8: Estimate after Phase 1 | G8: Separate phase | H8: TBD after Phase 1 | I8: Extend payment flow to Field Power/mobile/field sales
A11: Suggested Proposal Position
A12: 1 | B12: Offer Phase 0 as a paid fixed-scope discovery. This gives customer a low starting cost and gives Rikkeisoft enough facts to protect margin.
A13: 2 | B13: Use Lean Phase 1 as the base implementation. It covers business value without overbuilding exception handling or Field Power.
A14: 3 | B14: Quote Standard Phase 1 only if customer explicitly needs production-grade reconciliation and lower manual operations.
A15: 4 | B15: Keep Phase 2 as a separate post-MVP extension.

Sheet Work Breakdown
A1: Work Breakdown
A2: Editable man-day estimate by phase/workstream. Phase Estimates uses SUMIF formulas from this sheet.
A4: Phase | B4: Work Item | C4: Min MD | D4: Max MD | E4: Avg MD | F4: Criticality | G4: Notes
A5: P0 | B5: Requirement workshop and scope confirmation | C5: 1 | D5: 2 | E5: =(C5+D5)/2 -> 1.5 | F5: Must-have | G5: Confirm Counter Sales and Phase 2 boundary
A6: P0 | B6: SAP invoice/output review | C6: 1 | D6: 2 | E6: =(C6+D6)/2 -> 1.5 | F6: Must-have | G6: Identify ECC/S4/B1 and form technology
A7: P0 | B7: UOB API / PayNow QR feasibility review | C7: 1 | D7: 2 | E7: =(C7+D7)/2 -> 1.5 | F7: Must-have | G7: Confirm sandbox, OAuth2, QR data, webhook
A8: P0 | B8: Solution architecture and data flow | C8: 1 | D8: 1 | E8: =(C8+D8)/2 -> 1 | F8: Must-have | G8: Architecture, integration options, risk list
A9: P0 | B9: Final MVP estimation and delivery plan | C9: 1 | D9: 1 | E9: =(C9+D9)/2 -> 1 | F9: Must-have | G9: Basis for Phase 1 quote
A10: P1L | B10: Project setup and detailed design | C10: 2 | D10: 4 | E10: =(C10+D10)/2 -> 3 | F10: Must-have | G10: Keep design lean and implementation-ready
A11: P1L | B11: SAP invoice data mapping | C11: 2 | D11: 4 | E11: =(C11+D11)/2 -> 3 | F11: Must-have | G11: Invoice no, amount, customer, reference
A12: P1L | B12: SAP invoice output enhancement / QR placement | C12: 6 | D12: 10 | E12: =(C12+D12)/2 -> 8 | F12: Must-have | G12: Likely ABAP/form enhancement effort
A13: P1L | B13: Integration service setup | C13: 3 | D13: 5 | E13: =(C13+D13)/2 -> 4 | F13: Must-have | G13: Lightweight middleware/API service
A14: P1L | B14: UOB OAuth2 / API integration | C14: 4 | D14: 7 | E14: =(C14+D14)/2 -> 5.5 | F14: Must-have | G14: Token, certificates, bank API security
A15: P1L | B15: PayNow QR data generation/handling | C15: 3 | D15: 6 | E15: =(C15+D15)/2 -> 4.5 | F15: Must-have | G15: Dynamic amount and payment reference
A16: P1L | B16: Bank notification callback endpoint | C16: 4 | D16: 6 | E16: =(C16+D16)/2 -> 5 | F16: Must-have | G16: Receive UOB/SG Bank payment notification
... A32: P2 | B32: Testing and rollout support | C32: 6 | D32: 10 | E32: =(C32+D32)/2 -> 8 | F32: Phase 2 | G32: UAT and deployment support

Sheet Assumptions
A1: Assumptions and Scope Control
A2: Use these assumptions to keep Phase 1 small and protect margin.
A4: No. | B4: Assumption
A5: 1 | B5: Phase 1 covers Counter Sales only.
A6: 2 | B6: Currency is SGD.
A7: 3 | B7: PayNow Corporate / UEN registration is handled by SCSKAP/customer.
A8: 4 | B8: UOB provides API documentation, sandbox, credentials, certificate requirements, and webhook rules.
A9: 5 | B9: SAP version and output technology are available for review.
A10: 6 | B10: Existing invoice output exists and only needs QR/payment fields added.
A11: 7 | B11: One payment reference maps to one SAP invoice.
A12: 8 | B12: No partial payment, refund, chargeback, or multi-bank flow in Lean Phase 1.
A13: 9 | B13: SAP production transport and approval process are handled by SCSKAP/customer.
A17: Base Scope Exclusions
A18: 1 | B18: Bank onboarding delays and production approval/certification outside normal implementation support.
A19: 2 | B19: Refund, chargeback, multi-bank, multi-currency, or partial payment scenarios.
A20: 3 | B20: Major SAP invoice form redesign beyond QR/payment data placement.
A21: 4 | B21: Field Power Integration, dashboards, reporting portal, and advanced monitoring.
A22: 5 | B22: SAP infrastructure changes, customer network/firewall changes, or production transport approval delays.

Sheet Questions
A1: Questions Before Final Quote
A2: These must be answered before converting the MD range into a final fixed price.
A4: Topic | B4: Question | C4: Priority | D4: Owner/Status
A5: SAP version | B5: Which SAP version is used: ECC, S/4HANA On-Premise, S/4HANA Cloud, or SAP Business One? | C5: High | D5: Open
A6: Output technology | B6: Which invoice output technology is used: SAPscript, Smart Forms, Adobe Forms, or S/4HANA Output Management? | C6: High | D6: Open
A7: PayNow registration | B7: Does SCSKAP already have UOB PayNow Corporate registration and UEN suffix? | C7: High | D7: Open
A8: UOB API access | B8: Does UOB provide sandbox and API documentation for dynamic PayNow QR? | C8: High | D8: Open
A9: Notification method | B9: Is payment notification delivered by webhook/API, email, bank statement, or batch file? | C9: High | D9: Open
A10: SAP update | B10: Should SAP only mark payment status, or perform FI/AR clearing automatically? | C10: High | D10: Open
A11: Exception scope | B11: Are partial payment, overpayment, duplicate payment, and refund required in Phase 1? | C11: Medium | D11: Open
A12: Rollout scope | B12: Is Counter Sales one location/company code, or multiple? | C12: Medium | D12: Open
A13: Volume | B13: What is the expected transaction volume per day? | C13: Medium | D13: Open
A14: Timeline | B14: What is the target go-live date? | C14: Medium | D14: Open

Sheet Commercial Notes
A1: Commercial Notes
A2: Suggested language and guardrails for proposal discussions.
A4: Area | B4: Guidance
A5: Customer-facing answer | B5: Yes, this system can be developed. We recommend a short technical discovery first, then a focused Phase 1 for Counter Sales: PayNow QR embedded into SAP Sales Invoice, amount/reference auto-populated, UOB payment notification routed back, and SAP transaction confirmation.
A6: Budget strategy | B6: Start small. Phase 0 gives customer a low-cost entry point and lets Rikkeisoft avoid unsafe assumptions.
A7: Base offer | B7: Lean Phase 1 MVP. Keep advanced exception handling, dashboards, Field Power, refunds, partial payments, and multi-bank support outside base scope.
A8: Commercial model | B8: Phase 0 fixed price. Phase 1 fixed scope or capped T&M. Phase 2 separate estimate after Phase 1.
A9: Resource positioning | B9: English-speaking PM/engineer is required. ABAP support should be included or reserved depending on SAP output technology.
A10: Risk wording | B10: QR code generation is straightforward; the main risks are UOB API access/security, bank callback validation, SAP output changes, and SAP FI/AR reconciliation.
A11: Reference experience wording | B11: If exact PayNow/UOB/SAP reference is not verified, say Rikkeisoft has similar enterprise integration experience and will confirm exact reference internally.
A12: Do not include | B12: Do not include bank onboarding delays, major SAP redesign, full auto-clearing, Field Power, or advanced monitoring in the lowest-cost base quote.
A13: Presale next action | B13: Propose Phase 0 discovery with SCSKAP and UOB/SAP stakeholders.

Sheet References
A1: References
A2: Public source links used to ground the terminology and integration assumptions.
A4: Source | B4: Relevance | C4: URL
A5: ABS PayNow | B5: PayNow Corporate supports entities receiving SGD through UEN and QR payments. | C5: https://www.abs.org.sg/e-payments/pay-now
A6: UOB PayNow Corporate | B6: UOB supports PayNow Corporate and SGQR collection via UEN/QR. | C6: https://www.uobgroup.com.sg/business/transact/payments/paynow-corporate.page
A7: UOB API Services | B7: UOB API services include FAST/PayNow services and Credit/Debit Notification API. | C7: https://www.uobgroup.com/business/digital/uob-api-services.page
A8: SAP Invoice Forms | B8: SAP invoice forms/output can be configured for billing document printing/PDF output. | C8: https://help.sap.com/docs/SAP_S4HANA_CLOUD/ddd685ebd8614e7b8d8eaf4d001e7c40/7ea0b78d5d8e48b5a5078f618ce2a747.html

Sheet Noted
B1: Phase 1 Counter Sales:
A2: 1 | B2: Customer comes to counter.
A3: 2 | B3: Staff creates SAP Sales Invoice.
A4: 3 | B4: Invoice has PayNow QR.
A5: 4 | B5: Customer scans and pays at counter.
A6: 5 | B6: UOB sends payment notification.
A7: 6 | B7: SAP is updated.
B9: Phase 2 Field Power/mobile/field sales:
A10: 1 | B10: Salesperson or technician visits customer site. | C10: Why It Is More Complex Than Counter Sales
A11: 2 | B11: They use a mobile/tablet app. | C11: Field/mobile flow usually adds more work because:
A12: 3 | B12: They create invoice/payment request from the field.
A13: 4 | B13: App shows or generates PayNow QR. | C13: Mobile app may need online/offline support.
A14: 5 | B14: Customer scans and pays on-site. | C14: User may be outside company network.
A15: 6 | B15: UOB sends payment notification. | C15: Payment status must sync between mobile app, SAP, and bank.
A16: 7 | B16: SAP and the mobile/field system both show payment completed. | C16: QR may need to be shown on mobile instead of printed invoice.
C17: Need handle failed sync, duplicate payment, wrong amount, lost connection.
C18: Field users may need receipt/payment confirmation immediately.
B23: Chiến lược nên dùng
B24: Vì khách nói budget thấp, không nên báo giá full scope ngay. Cách tiếp cận tốt nhất là chia thành:
B26: Phase 0 - Paid discovery/design nhỏ
B27: Mục tiêu: xác nhận SAP version, invoice output, UOB API, webhook, QR format, reconciliation rule.
B28: Effort: 5-8 MD
B30: Phase 1 - Lean MVP cho Counter Sales
B31: Chỉ làm phần tạo QR trên SAP invoice, scan PayNow, nhận notification từ UOB/SG Bank, match invoice reference, cập nhật/confirm SAP.
B32: Effort: 45-75 MD
B34: Phase 2 - Field Power Integration
B35: Để sau, không đưa vào base price.
B36: Effort: 30-50 MD
